emu21cmfast/__init__.py
emu21cmfast/config.py
emu21cmfast/emulator.py
emu21cmfast/emulator_constants.npz
emu21cmfast/get_emulator.py
emu21cmfast-1.0.0.dist-info/LICENSE
emu21cmfast-1.0.0.dist-info/METADATA
emu21cmfast-1.0.0.dist-info/WHEEL
emu21cmfast-1.0.0.dist-info/entry_points.txt
emu21cmfast-1.0.0.dist-info/RECORD
