Metadata-Version: 2.1
Name: emu21cmfast
Version: 1.0.0
Summary: Emulator of 21cmFAST summaries.
Home-page: https://github.com/21cmFAST/EMU21cmFAST
License: MIT
Keywords: Epoch of Reionization,Cosmology
Author: Daniela Breitman
Author-email: daniela.breitman@sns.it
Requires-Python: >=3.8,<3.12
Classifier: Development Status :: 5 - Production/Stable
Classifier: License :: OSI Approved :: MIT License
Classifier: Operating System :: POSIX
Classifier: Operating System :: Unix
Classifier: Programming Language :: Python
Classifier: Programming Language :: Python :: 3
Classifier: Programming Language :: Python :: 3.8
Classifier: Programming Language :: Python :: 3.9
Classifier: Programming Language :: Python :: 3.10
Classifier: Programming Language :: Python :: 3.11
Classifier: Programming Language :: Python :: 3.10
Classifier: Programming Language :: Python :: 3.7
Classifier: Programming Language :: Python :: 3.8
Classifier: Programming Language :: Python :: 3.9
Requires-Dist: 21cmfast (>=3.2.0,<4.0.0)
Requires-Dist: appdirs (>=1.4.4,<2.0.0)
Requires-Dist: click (>=8.0.1)
Requires-Dist: numpy (>=1.24.2,<2.0.0)
Requires-Dist: scipy (>=1.10.1,<2.0.0)
Requires-Dist: tensorflow (>=2.11.0,<3.0.0)
Requires-Dist: toml (>=0.10.2,<0.11.0)
Project-URL: Changelog, https://github.com/21cmFAST/EMU21cmFAST/releases
Project-URL: Documentation, https://EMU21cmFAST.readthedocs.io
Project-URL: Repository, https://github.com/21cmFAST/EMU21cmFAST
